MANIFEST.in
README.md
setup.py
PyGFETdb/AnalyzeData.py
PyGFETdb/BiosensAnalysis.py
PyGFETdb/Connection.bin
PyGFETdb/DBAnalyze.py
PyGFETdb/DBCore2.py
PyGFETdb/DBInterface.py
PyGFETdb/DBSearch.py
PyGFETdb/DBXlsReport.py
PyGFETdb/DataClass.py
PyGFETdb/DataStructures.py
PyGFETdb/NoiseModel.py
PyGFETdb/PlotDataClass.py
PyGFETdb/__init__.py
PyGFETdb/ws_json_class.py
PyGFETdb.egg-info/PKG-INFO
PyGFETdb.egg-info/SOURCES.txt
PyGFETdb.egg-info/dependency_links.txt
PyGFETdb.egg-info/entry_points.txt
PyGFETdb.egg-info/top_level.txt
PyGFETdb/GuiDBView/ClassQueries.py
PyGFETdb/GuiDBView/GuiDBViewDataExplorer.py
PyGFETdb/GuiDBView/GuiDBView_v2.py
PyGFETdb/GuiDBView/GuiDBView_v2.ui
PyGFETdb/GuiDBView/GuiDataExplorer.ui
PyGFETdb/GuiDBView/GuiDataExplorer_v2.ui
PyGFETdb/GuiDBView/GuiHelpers.py
PyGFETdb/GuiDBView/GuiNormalization.ui
PyGFETdb/GuiDBView/NormGui.py
PyGFETdb/GuiDBView/UpdateDialogs.py
PyGFETdb/GuiDBView/__init__.py